lsjsonclasses/__init__.py
lsjsonclasses-2.0.1.dist-info/METADATA
lsjsonclasses-2.0.1.dist-info/WHEEL
lsjsonclasses-2.0.1.dist-info/entry_points.txt
lsjsonclasses-2.0.1.dist-info/RECORD
